xraybot/__init__.py
xraybot/__version__.py
xraybot/_context.py
xraybot/_data.py
xraybot/_utils.py
xraybot/_worker.py
xraybot/_xray_bot.py
xray_bot-1.0.0.dist-info/LICENSE
xray_bot-1.0.0.dist-info/METADATA
xray_bot-1.0.0.dist-info/WHEEL
xray_bot-1.0.0.dist-info/top_level.txt
xray_bot-1.0.0.dist-info/RECORD
