Metadata-Version: 2.1
Name: xray-bot
Version: 1.0.0
Summary: Synchronize atlassian xray test case tickets with your test code and upload the test results
Author-email: "Johnny.H" <jnhyperion@gmail.com>
Keywords: atlassian,xray,automation
Classifier: Programming Language :: Python :: 3
Classifier: Operating System :: OS Independent
Requires-Python: >=3.8.1
License-File: LICENSE
Requires-Dist: atlassian-python-api==4.0.5
Requires-Dist: retry
Provides-Extra: dev
Requires-Dist: pre-commit; extra == "dev"
Requires-Dist: invoke; extra == "dev"
Requires-Dist: pytest; extra == "dev"
Requires-Dist: pytest-cov; extra == "dev"
